[
  {
    "entry_date": "2026-03-21",
    "mood_key": "anxious",
    "note": "COLOR MOOD DIARY аа олон янзаар туршаад ажиллах болов уу алдаа битгий гараасай гэж түгшсэн өдөр байна кк",
    "intensity": 1,
    "tags": [
      "Гэртээ"
    ],
    "reflections": [
      {
        "date": "2026-03-23",
        "text": "Маш сайхан ажиллаж байгаад сэтгэл ханамжтай байна"
      }
    ]
  },
  {
    "entry_date": "2026-03-22",
    "mood_key": "happy",
    "note": "Өнөөдөр маш сайхан үр бүтээлтэй, кодоо бичсэн, постоо хийсэн, гэрээ цэвэрлэсэн тайван өдөр байна. Vibe Coding маань амжилттай алдаагүй ажиллаж байгаа учир аз жаргал мэдрэгдэж байнаа",
    "intensity": 5,
    "tags": [
      "Гэртээ"
    ],
    "reflections": [
      {
        "date": "2026-03-22",
        "text": "Сайн байна"
      },
      {
        "date": "2026-03-23",
        "text": "Аймар үр бүтээлтэй байсан байна шд кк"
      }
    ]
  },
  {
    "entry_date": "2026-03-23",
    "mood_key": "calm",
    "note": "Бүх зүйл тайван жирийн сайхан өдөр байна. Гэхдээ өнөөдөр site-аа deployment хийж үзэх ёстой. Юу болохнуу харж л байя",
    "intensity": 5,
    "tags": [],
    "reflections": [
      {
        "date": "2026-03-23",
        "text": "Good"
      }
    ]
  },
  {
    "entry_date": "2026-03-24",
    "mood_key": "calm",
    "note": "Гадуур гарч ажил амжууллаа. Гадаа салхитай муухай өдөр байсан ч сэтгэл санаа тайван байна. Одоо site-аа deylpoyment хийх гээд сууж байна.",
    "intensity": 3,
    "tags": [
      "Гадуур",
      "Ажил"
    ],
    "reflections": []
  }
]